AUTHORS
COPYRIGHT
ChangeLog
MANIFEST.in
NEWS
README
README.PackageKit
README.tests
TODO
applet.py
aptd
aptdcon
gtk-demo.py
gtk3-demo.py
pylintrc
release.sh
setup.cfg
setup.py
apport/aptdaemon.py
aptdaemon/__init__.py
aptdaemon/client.py
aptdaemon/config.py
aptdaemon/console.py
aptdaemon/core.py
aptdaemon/crash.py
aptdaemon/debconf.py
aptdaemon/enums.py
aptdaemon/errors.py
aptdaemon/gtk3widgets.py
aptdaemon/gtkwidgets.py
aptdaemon/lock.py
aptdaemon/logger.py
aptdaemon/loop.py
aptdaemon/networking.py
aptdaemon/pkcompat.py
aptdaemon/pkenums.py
aptdaemon/policykit1.py
aptdaemon/progress.py
aptdaemon/test.py
aptdaemon/utils.py
aptdaemon/worker.py
aptdaemon.egg-info/PKG-INFO
aptdaemon.egg-info/SOURCES.txt
aptdaemon.egg-info/dependency_links.txt
aptdaemon.egg-info/top_level.txt
data/20dbus
data/org.debian.apt.conf
data/org.debian.apt.policy.in
data/org.debian.apt.service
data/org.freedesktop.PackageKit-aptd.conf
data/org.freedesktop.PackageKit.service
data/icons/clean_svg_icons.sh
data/icons/generate_16x16_icons.sh
data/icons/generate_24x24_icons.sh
data/icons/generate_48x48_icons.sh
data/icons/16x16/animations/aptdaemon-action-cleaning-up.png
data/icons/16x16/animations/aptdaemon-action-downloading.png
data/icons/16x16/animations/aptdaemon-action-installing.png
data/icons/16x16/animations/aptdaemon-action-removing.png
data/icons/16x16/animations/aptdaemon-action-resolving.png
data/icons/16x16/animations/aptdaemon-action-updating-cache.png
data/icons/16x16/animations/aptdaemon-action-waiting.png
data/icons/16x16/status/aptdaemon-add.png
data/icons/16x16/status/aptdaemon-cleanup.png
data/icons/16x16/status/aptdaemon-delete.png
data/icons/16x16/status/aptdaemon-download.png
data/icons/16x16/status/aptdaemon-resolve.png
data/icons/16x16/status/aptdaemon-update-cache.png
data/icons/16x16/status/aptdaemon-upgrade.png
data/icons/16x16/status/aptdaemon-wait.png
data/icons/16x16/status/aptdaemon-working.png
data/icons/22x22/animations/aptdaemon-action-cleaning-up.png
data/icons/22x22/animations/aptdaemon-action-downloading.png
data/icons/22x22/animations/aptdaemon-action-installing.png
