Metadata-Version: 1.1
Name: aptdaemon
Version: 1.1.1
Summary: DBus driven daemon for APT
Home-page: http://launchpad.net/sessioninstaller
Author: Sebastian Heinlein
Author-email: devel@glatzor.de
License: GNU LGPL
Keywords: apt package manager deb dbus d-bus debian ubuntu dpkg
Platform: posix
Classifier: Development Status :: 5 - Production/Stable
Classifier: Intended Audience :: System Administrators
Classifier: License :: OSI Approved :: GNU Library or Lesser General Public License (LGPL)
Classifier: Programming Language :: Python :: 2.6
Classifier: Topic :: System :: Systems Administration
Classifier: Topic :: System :: Software Distribution
